psindex/__init__.py
psindex-0.0.2.dist-info/LICENSE
psindex-0.0.2.dist-info/METADATA
psindex-0.0.2.dist-info/WHEEL
psindex-0.0.2.dist-info/top_level.txt
psindex-0.0.2.dist-info/RECORD
